LICENSE
setup.cfg
setup.py
internode/__init__.py
internode.egg-info/PKG-INFO
internode.egg-info/SOURCES.txt
internode.egg-info/dependency_links.txt
internode.egg-info/requires.txt
internode.egg-info/top_level.txt