Metadata-Version: 2.1
Name: internode
Version: 1.5.5
Summary: Python library to access the Internode API: https://customer-webtools-api.internode.on.net/api/v1.5
Home-page: https://github.com/leighcurran/AuroraPlus
Author: Leigh Curran
Author-email: InternodePy@outlook.com
License: MIT
Keywords: Internode,API
Platform: UNKNOWN
Classifier: Development Status :: 4 - Beta
Classifier: Intended Audience :: Developers
Classifier: Topic :: Software Development :: Build Tools
Classifier: License :: OSI Approved :: MIT License
Classifier: Programming Language :: Python :: 3.5
Classifier: Programming Language :: Python :: 3.6
Classifier: Programming Language :: Python :: 3.7
Classifier: Programming Language :: Python :: 3.8
Classifier: Programming Language :: Python :: 3.9
License-File: LICENSE
